pycogent.py
pycogent-0.0.3.dist-info/LICENSE
pycogent-0.0.3.dist-info/METADATA
pycogent-0.0.3.dist-info/WHEEL
pycogent-0.0.3.dist-info/top_level.txt
pycogent-0.0.3.dist-info/RECORD
