Metadata-Version: 2.1
Name: pycogent
Version: 0.0.3
Summary: Post-processing tools for COGENT plasma simulation code
Home-page: https://github.com/arknyazev/pycogent
Author: Alex Knyazev
Author-email: aknyazev@ucsd.edu
License: UNKNOWN
Platform: UNKNOWN
Classifier: Programming Language :: Python :: 3
Classifier: License :: OSI Approved :: MIT License
Classifier: Operating System :: OS Independent
Requires-Dist: matplotlib
Requires-Dist: numpy
Requires-Dist: h5py
Provides-Extra: dev
Requires-Dist: pytest (>=3.7) ; extra == 'dev'
